week2_combinational_logic/01_mux/mux2.v
module mux2_assign(
	output o_out,
	input  i_sel,
	input  i_in0,
	input  i_in1
);

	assign o_out = i_sel ? i_in0 : i_in1;

endmodule

module mux2_if(
	output reg o_out,
 	input      i_sel,
	input      i_in0,
	input	   i_in1
);
	

	always @(*) begin
		if(i_sel == 0) begin
			o_out = i_in0;
		end
		else begin 
			o_out = i_in1;
		end
	end
endmodule


module mux2_case(
	output reg o_out,
 	input      i_sel,
	input      i_in0,
	input	   i_in1
);

	always @(*) begin
		case(i_sel)
			0: 		o_out = i_in0;
			1: 		o_out = i_in1;
		endcase
	end
endmodule

week2_combinational_logic/01_mux/mux2_tb.v
`timescale 1ns/1ps
`include "mux2.v"

module mux2_tb;

//=========================================
// module instanciation
//=========================================

	wire	 o_out_assign;
	wire	 o_out_if;
	wire	 o_out_case;
	reg 	 i_sel;
	reg		 i_in0;
	reg		 i_in1;

mux2_assign u_mux2_assign(
	 .o_out(o_out_assign),
	 .i_sel(i_sel),
	 .i_in0(i_in0),
	 .i_in1(i_in1)
);

mux2_if u_mux2_if(
	 .o_out(o_out_if),
	 .i_sel(i_sel),
	 .i_in0(i_in0),
	 .i_in1(i_in1)
);


mux2_case u_mux2_case(
	 .o_out(o_out_case),
	 .i_sel(i_sel),
	 .i_in0(i_in0),
	 .i_in1(i_in1)
);

//=========================================
// input Stimulus
//=========================================

	integer i;
    initial begin
		for(i=0; i<10; i++) begin
			{i_sel, i_in0, i_in1} = $urandom_range(0,7);
			#(100);
		end
	end

	reg [8*32-1:0] vcd_file;

	initial begin 
		if($value$plusargs("vcd_file=%s", vcd_file)) begin 
		   $dumpfile(vcd_file);
		   $dumpvars;
		end
	end 

endmodule

week2_combinational_logic/01_mux/vcd/mux2.vcd
$date
	Mon Jun 24 10:43:00 2024
$end
$version
	Icarus Verilog
$end
$timescale
	1ps
$end
$scope module mux2_tb $end
$var wire 1 ! o_out_if $end
$var wire 1 " o_out_case $end
$var wire 1 # o_out_assign $end
$var reg 1 $ i_in0 $end
$var reg 1 % i_in1 $end
$var reg 1 & i_sel $end
$var reg 256 ' vcd_file [255:0] $end
$var integer 32 ( i [31:0] $end
$scope module u_mux2_assign $end
$var wire 1 $ i_in0 $end
$var wire 1 % i_in1 $end
$var wire 1 & i_sel $end
$var wire 1 # o_out $end
$upscope $end
$scope module u_mux2_case $end
$var wire 1 $ i_in0 $end
$var wire 1 % i_in1 $end
$var wire 1 & i_sel $end
$var reg 1 " o_out $end
$upscope $end
$scope module u_mux2_if $end
$var wire 1 $ i_in0 $end
$var wire 1 % i_in1 $end
$var wire 1 & i_sel $end
$var reg 1 ! o_out $end
$upscope $end
$upscope $end
$enddefinitions $end
#0
$dumpvars
b0 (
b10111000101111011101100110001101100100001011110110110101110101011110000011001000101110011101100110001101100100 '
1&
0%
0$
0#
0"
0!
$end
#100000
1!
1"
0&
1$
b1 (
#200000
0"
0!
0$
b10 (
#300000
1#
1%
b11 (
#400000
0#
1&
0%
b100 (
#500000
1#
1$
b101 (
#600000
0&
0$
1%
b110 (
#700000
0#
0%
b111 (
#800000
1&
b1000 (
#900000
b1001 (
#1000000
b1010 (
