project/verilog_tutorials/verilator/1_basic/counter.v
module counter 
#(
	parameter UPBND	 = 15	
)(
	output reg [$clog2(UPBND+1)-1:0] o_cnt,
	input 						     i_clk,
	input							 i_rstn
);

	always @(posedge i_clk or negedge i_rstn) begin
		if(!i_rstn) begin
			o_cnt <= 0;
		end else begin
			if(o_cnt == UPBND) begin
				o_cnt <= 0;
			end else begin 
				o_cnt <= o_cnt + 1;
			end 
		end
	end
endmodule

project/verilog_tutorials/verilator/1_basic/counter.vcd
$version Generated by VerilatedVcd $end
$date Wed Jul 24 16:12:09 2024
 $end
$timescale   1ps $end

 $scope module TOP $end
  $var wire  1 $ i_clk $end
  $var wire  1 % i_rstn $end
  $var wire  4 # o_cnt [3:0] $end
  $scope module counter $end
   $var wire 32 & UPBND [31:0] $end
   $var wire  1 $ i_clk $end
   $var wire  1 % i_rstn $end
   $var wire  4 # o_cnt [3:0] $end
  $upscope $end
 $upscope $end
$enddefinitions $end


#0
b0000 #
1$
0%
b00000000000000000000000000001111 &
#1
0$
#2
1$
#3
0$
#4
1$
#5
0$
1%
#6
b0001 #
1$
#7
0$
#8
b0010 #
1$
#9
0$
#10
b0011 #
1$
#11
0$
#12
b0100 #
1$
#13
0$
#14
b0101 #
1$
#15
0$
#16
b0110 #
1$
#17
0$
#18
b0111 #
1$
