week2_combinational_logic/03_param/mux2.v
module mux2_assign
#(
	parameter 	BW_DATA = 4
)
(
	output [BW_DATA-1:0] o_out,
	input  [BW_DATA-1:0] i_sel,
	input  [BW_DATA-1:0] i_in0,
	input  [BW_DATA-1:0] i_in1
);

	assign o_out = i_sel ? i_in0 : i_in1;

endmodule

module mux2_if
#(
	parameter 	BW_DATA = 4
)
(
	output reg [BW_DATA-1:0] o_out,
 	input      [BW_DATA-1:0] i_sel,
	input      [BW_DATA-1:0] i_in0,
	input	   [BW_DATA-1:0] i_in1
);

	always @(*) begin
		if(i_sel == 0) begin
			o_out = i_in0;
		end
		else begin 
			o_out = i_in1;
		end
	end
endmodule


module mux2_case
#(
	parameter 	BW_DATA = 4
)
(
	output reg [BW_DATA-1:0] o_out,
 	input      [BW_DATA-1:0] i_sel,
	input      [BW_DATA-1:0] i_in0,
	input	   [BW_DATA-1:0] i_in1
);

	always @(*) begin
		case(i_sel)
			0: 		o_out = i_in0;
			1: 		o_out = i_in1;
		endcase
	end
endmodule

week2_combinational_logic/03_param/mux2_tb.v
`define BW_DATA 	4
`include "mux2.v"

module mux2_tb;

//=========================================
// module instanciation
//=========================================
	parameter BW_DATA = 4;
	wire	[BW_DATA-1:0]  o_out_assign;
	wire	[BW_DATA-1:0]  o_out_if;
	wire	[BW_DATA-1:0]  o_out_case;
	reg 	[BW_DATA-1:0]  i_sel;
	reg		[BW_DATA-1:0]  i_in0;
	reg		[BW_DATA-1:0]  i_in1;

mux2_assign u_mux2_assign(
	 .o_out(o_out_assign),
	 .i_sel(i_sel),
	 .i_in0(i_in0),
	 .i_in1(i_in1)
);

mux2_if u_mux2_if(
	 .o_out(o_out_if),
	 .i_sel(i_sel),
	 .i_in0(i_in0),
	 .i_in1(i_in1)
);


mux2_case u_mux2_case(
	 .o_out(o_out_case),
	 .i_sel(i_sel),
	 .i_in0(i_in0),
	 .i_in1(i_in1)
);

//=========================================
// input Stimulus
//=========================================

	integer i;
    initial begin
		for(i=0; i<10; i++) begin
			{i_sel, i_in0, i_in1} = $urandom_range(0,7);
			#(100);
		end
	end

	reg [8*32-1:0] vcd_file;

	initial begin 
		if($value$plusargs("vcd_file=%s", vcd_file)) begin 
		   $dumpfile(vcd_file);
		   $dumpvars;
		end
	end 

endmodule

week2_combinational_logic/03_param/vcd/mux2.vcd
$date
	Thu Jun 20 19:02:30 2024
$end
$version
	Icarus Verilog
$end
$timescale
	1s
$end
$scope module mux2_tb $end
$var wire 4 ! o_out_if [3:0] $end
$var wire 4 " o_out_case [3:0] $end
$var wire 4 # o_out_assign [3:0] $end
$var reg 4 $ i_in0 [3:0] $end
$var reg 4 % i_in1 [3:0] $end
$var reg 4 & i_sel [3:0] $end
$var reg 256 ' vcd_file [255:0] $end
$var integer 32 ( i [31:0] $end
$scope module u_mux2_assign $end
$var wire 4 ) i_in0 [3:0] $end
$var wire 4 * i_in1 [3:0] $end
$var wire 4 + i_sel [3:0] $end
$var wire 4 , o_out [3:0] $end
$upscope $end
$scope module u_mux2_case $end
$var wire 4 - i_in0 [3:0] $end
$var wire 4 . i_in1 [3:0] $end
$var wire 4 / i_sel [3:0] $end
$var reg 4 0 o_out [3:0] $end
$upscope $end
$scope module u_mux2_if $end
$var wire 4 1 i_in0 [3:0] $end
$var wire 4 2 i_in1 [3:0] $end
$var wire 4 3 i_sel [3:0] $end
$var reg 4 4 o_out [3:0] $end
$upscope $end
$upscope $end
$enddefinitions $end
#0
$dumpvars
b0 4
b0 3
b100 2
b0 1
b0 0
b0 /
b100 .
b0 -
b100 ,
b0 +
b100 *
b0 )
b0 (
b10111000101111011101100110001101100100001011110110110101110101011110000011001000101110011101100110001101100100 '
b0 &
b100 %
b0 $
b100 #
b0 "
b0 !
$end
#100
b10 #
b10 ,
b10 %
b10 *
b10 .
b10 2
b1 (
#200
b0 #
b0 ,
b0 %
b0 *
b0 .
b0 2
b10 (
#300
b1 #
b1 ,
b1 %
b1 *
b1 .
b1 2
b11 (
#400
b100 #
b100 ,
b100 %
b100 *
b100 .
b100 2
b100 (
#500
b110 #
b110 ,
b110 %
b110 *
b110 .
b110 2
b101 (
#600
b1 #
b1 ,
b1 %
b1 *
b1 .
b1 2
b110 (
#700
b0 #
b0 ,
b0 %
b0 *
b0 .
b0 2
b111 (
#800
b100 #
b100 ,
b100 %
b100 *
b100 .
b100 2
b1000 (
#900
b1001 (
#1000
b1010 (
