week2_combinational_logic/02_4bit_adder/adder_4bit.v
module adder_4bit_dataflow
(
	output [3:0] o_s,
	output 		 o_c,
	input  [3:0] i_a,
	input  [3:0] i_b,
	input 		 i_c
);

	assign {o_s, o_c} = i_a + i_b + i_c;

endmodule

week2_combinational_logic/02_4bit_adder/adder_4bit_tb.v
`include "adder_4bit.v"

module adder_4bit_tb;

//=========================================
// module instanciation
//=========================================

wire [3:0] o_s;
wire 	   o_c;
reg  [3:0] i_a;
reg  [3:0] i_b;
reg        i_c;
reg  [4:0] sum;
reg 	   CLK;

adder_4bit_dataflow u_adder_4bit_dataflow
(
	.o_s(o_s),
	.o_c(o_c),
	.i_a(i_a),
	.i_b(i_b),
	.i_c(i_c)
);

//=========================================
// input Stimulus
//=========================================

integer i;

initial begin
	for(i=0; i<10; i++) begin
		i_a = 4'h1;
		i_b = 4'h8;
		i_c = 1'h1;

		sum = i_a + i_b + i_c;
		$display("{o_c, o_s} = %h", sum);
		#100;
	end
	$finish;
end

reg [8*32-1:0] vcd_file;

initial begin 
	if($value$plusargs("vcd_file=%s", vcd_file)) begin 
	   $dumpfile(vcd_file);
	   $dumpvars;
	end
end 
endmodule

week2_combinational_logic/02_4bit_adder/vcd/adder_4bit.vcd
$date
	Mon Jun 24 10:40:21 2024
$end
$version
	Icarus Verilog
$end
$timescale
	1s
$end
$scope module adder_4bit_tb $end
$var wire 4 ! o_s [3:0] $end
$var wire 1 " o_c $end
$var reg 4 # i_a [3:0] $end
$var reg 4 $ i_b [3:0] $end
$var reg 1 % i_c $end
$var reg 5 & sum [4:0] $end
$var reg 256 ' vcd_file [255:0] $end
$var integer 32 ( i [31:0] $end
$scope module u_adder_4bit_dataflow $end
$var wire 4 ) i_a [3:0] $end
$var wire 4 * i_b [3:0] $end
$var wire 1 % i_c $end
$var wire 4 + o_s [3:0] $end
$var wire 1 " o_c $end
$upscope $end
$upscope $end
$enddefinitions $end
#0
$dumpvars
b101 +
b1000 *
b1 )
b0 (
b10111000101111011101100110001101100100001011110110000101100100011001000110010101110010010111110011010001100010011010010111010000101110011101100110001101100100 '
b1010 &
1%
b1000 $
b1 #
0"
b101 !
$end
#100
b1 (
#200
b10 (
#300
b11 (
#400
b100 (
#500
b101 (
#600
b110 (
#700
b111 (
#800
b1000 (
#900
b1001 (
#1000
b1010 (
