week3_sequential_logic/08_Register/regfile.v
module regfile
#(
	parameter MIF_FILE	= "regfile.mif",
	parameter BW_DATA 	= 32,
	parameter BW_ADDR	= 5
)
(
	output [BW_DATA-1:0] o_rf_rd_data0,
	output [BW_DATA-1:0] o_rf_rd_data1,
	input  [BW_ADDR-1:0] i_rf_rd_addr0,
	input  [BW_ADDR-1:0] i_rf_rd_addr1,
	input  [BW_DATA-1:0] i_rf_wr_data,
	input  [BW_ADDR-1:0] i_rf_wr_addr,
	input				 i_rf_wr_en,
	input				 i_clk
);

	reg		[BW_DATA-1:0]	rf_arr[0:2**BW_ADDR-1];

	`ifdef  MIF_FILE
		initial begin 
			$readmemh(MIF_FILE, rf_arr);
			// $readmemb(MIF_FILE, rf_arr);
		end
	`endif


	assign	o_rf_rd_data0 	= rf_arr[i_rf_rd_addr0];
	assign  o_rf_rd_data1	= rf_arr[i_rf_rd_addr1];

	always @(posedge i_clk) begin
		if(i_rf_wr_en) begin
			rf_arr[i_rf_wr_addr] <= i_rf_wr_data;
		end else begin 
			rf_arr[i_rf_wr_addr] <= rf_arr[i_rf_wr_addr];
		end
	end

endmodule

week3_sequential_logic/08_Register/regfile_tb.v
`define BW_DATA		16
`define BW_ADDR 	4
`define CLKFREQ		100
`define SIMCYCLE	2**`BW_ADDR

`include "regfile.v"

`define MIF_FILE


module regfile_tb;

	wire [`BW_DATA-1:0] o_rf_rd_data0;
	wire [`BW_DATA-1:0] o_rf_rd_data1;
	reg  [`BW_ADDR-1:0] i_rf_rd_addr0;
	reg  [`BW_ADDR-1:0] i_rf_rd_addr1;
	reg  [`BW_DATA-1:0] i_rf_wr_data;
	reg  [`BW_ADDR-1:0] i_rf_wr_addr;
	reg				 	i_rf_wr_en;
	reg				 	i_clk;

	regfile
	#(
		.BW_DATA			(`BW_DATA			),
		.BW_ADDR			(`BW_ADDR			)
	)
	u_regfile(
		.o_rf_rd_data0		(o_rf_rd_data0		),
		.o_rf_rd_data1		(o_rf_rd_data1		),
		.i_rf_rd_addr0		(i_rf_rd_addr0		),
		.i_rf_rd_addr1		(i_rf_rd_addr1		),
		.i_rf_wr_data		(i_rf_wr_data		),
		.i_rf_wr_addr		(i_rf_wr_addr		),
		.i_rf_wr_en			(i_rf_wr_en			),
		.i_clk				(i_clk				)
	);

//------------------------------------------------
// Clock
//------------------------------------------------
	
	always #(500/`CLKFREQ) i_clk = ~i_clk;

//------------------------------------------------
// Tasks
//------------------------------------------------

	reg [8*30-1:0] 		taskState;

	task init;
		begin 
			i_rf_rd_addr0		= 0;	
            i_rf_rd_addr1		= 0;
            i_rf_wr_data		= 0;
            i_rf_wr_addr	    = 0;	
            i_rf_wr_en			= 0;
            i_clk				= 0;
		end
	endtask

	task regWR;
		input [`BW_ADDR-1:0] ti_rf_wr_addr;
		input [`BW_DATA-1:0] ti_rf_wr_data;
		begin
			@(negedge i_clk) begin
				taskState		= 	"WR";
				i_rf_wr_data 	=	ti_rf_wr_data;
				i_rf_wr_addr 	=	ti_rf_wr_addr;
				i_rf_wr_en		= 	1;
			end
		end
	endtask

	task regRD;
		input [`BW_ADDR-1:0] ti_rf_rd_addr0;
		input [`BW_ADDR-1:0] ti_rf_rd_addr1;
		begin
			@(negedge i_clk) begin
				taskState		= 	"RD";
				i_rf_rd_addr0 	=	ti_rf_rd_addr0;
				i_rf_rd_addr1	=	ti_rf_rd_addr1;
				i_rf_wr_en		= 	0;
			end
		end
	endtask

//------------------------------------------------
// Test stimulus
//------------------------------------------------
	
	integer i, j;
	initial begin 
		init();
		#(4*1000/`CLKFREQ);
		for(i=0; i<`SIMCYCLE; i++) begin 
			regWR(i, i);
		end
		
		for(i=0; i<`SIMCYCLE; i++) begin 
			regRD(i, i);
		end

		for(i=0; i<`SIMCYCLE; i++) begin 
			regWR(i, $urandom_range(0, 2**`BW_DATA-1));
			#(1000/`CLKFREQ);
			regRD(i ,i);
		end
		$finish;
	end
	
//---------------------------------------------
// Dump VCD  
//---------------------------------------------

    reg [8*32-1:0] vcd_file;
    initial begin
        if($value$plusargs("vcd_file=%s", vcd_file)) begin
            $dumpfile(vcd_file);
            $dumpvars;
			for (i=0; i<2**`BW_ADDR; i++) begin 
				$dumpvars(0,u_regfile.rf_arr[i]);
			end
			$dumpvars;
        end else begin
            $dumpfile("regfile_tb.vcd");
            $dumpvars;
        end
    end
endmodule

week3_sequential_logic/08_Register/vcd/regfile.vcd
$date
	Thu Jun 27 15:40:34 2024
$end
$version
	Icarus Verilog
$end
$timescale
	1s
$end
$scope module regfile_tb $end
$var wire 16 ! o_rf_rd_data1 [15:0] $end
$var wire 16 " o_rf_rd_data0 [15:0] $end
$var reg 1 # i_clk $end
$var reg 4 $ i_rf_rd_addr0 [3:0] $end
$var reg 4 % i_rf_rd_addr1 [3:0] $end
$var reg 4 & i_rf_wr_addr [3:0] $end
$var reg 16 ' i_rf_wr_data [15:0] $end
$var reg 1 ( i_rf_wr_en $end
$var reg 240 ) taskState [239:0] $end
$var reg 256 * vcd_file [255:0] $end
$var integer 32 + i [31:0] $end
$scope module u_regfile $end
$var wire 1 # i_clk $end
$var wire 4 , i_rf_rd_addr0 [3:0] $end
$var wire 4 - i_rf_rd_addr1 [3:0] $end
$var wire 4 . i_rf_wr_addr [3:0] $end
$var wire 16 / i_rf_wr_data [15:0] $end
$var wire 1 ( i_rf_wr_en $end
$var wire 16 0 o_rf_rd_data0 [15:0] $end
$var wire 16 1 o_rf_rd_data1 [15:0] $end
$upscope $end
$scope task init $end
$upscope $end
$scope task regRD $end
$var reg 4 2 ti_rf_rd_addr0 [3:0] $end
$var reg 4 3 ti_rf_rd_addr1 [3:0] $end
$upscope $end
$scope task regWR $end
$var reg 4 4 ti_rf_wr_addr [3:0] $end
$var reg 16 5 ti_rf_wr_data [15:0] $end
$upscope $end
$upscope $end
$scope module regfile_tb $end
$scope module u_regfile $end
$var reg 16 6 \rf_arr[0] [15:0] $end
$upscope $end
$upscope $end
$scope module regfile_tb $end
$scope module u_regfile $end
$var reg 16 7 \rf_arr[1] [15:0] $end
$upscope $end
$upscope $end
$scope module regfile_tb $end
$scope module u_regfile $end
$var reg 16 8 \rf_arr[2] [15:0] $end
$upscope $end
$upscope $end
$scope module regfile_tb $end
$scope module u_regfile $end
$var reg 16 9 \rf_arr[3] [15:0] $end
$upscope $end
$upscope $end
$scope module regfile_tb $end
$scope module u_regfile $end
$var reg 16 : \rf_arr[4] [15:0] $end
$upscope $end
$upscope $end
$scope module regfile_tb $end
$scope module u_regfile $end
$var reg 16 ; \rf_arr[5] [15:0] $end
$upscope $end
$upscope $end
$scope module regfile_tb $end
$scope module u_regfile $end
$var reg 16 < \rf_arr[6] [15:0] $end
$upscope $end
$upscope $end
$scope module regfile_tb $end
$scope module u_regfile $end
$var reg 16 = \rf_arr[7] [15:0] $end
$upscope $end
$upscope $end
$scope module regfile_tb $end
$scope module u_regfile $end
$var reg 16 > \rf_arr[8] [15:0] $end
$upscope $end
$upscope $end
$scope module regfile_tb $end
$scope module u_regfile $end
$var reg 16 ? \rf_arr[9] [15:0] $end
$upscope $end
$upscope $end
$scope module regfile_tb $end
$scope module u_regfile $end
$var reg 16 @ \rf_arr[10] [15:0] $end
$upscope $end
$upscope $end
$scope module regfile_tb $end
$scope module u_regfile $end
$var reg 16 A \rf_arr[11] [15:0] $end
$upscope $end
$upscope $end
$scope module regfile_tb $end
$scope module u_regfile $end
$var reg 16 B \rf_arr[12] [15:0] $end
$upscope $end
$upscope $end
$scope module regfile_tb $end
$scope module u_regfile $end
$var reg 16 C \rf_arr[13] [15:0] $end
$upscope $end
$upscope $end
$scope module regfile_tb $end
$scope module u_regfile $end
$var reg 16 D \rf_arr[14] [15:0] $end
$upscope $end
$upscope $end
$scope module regfile_tb $end
$scope module u_regfile $end
$var reg 16 E \rf_arr[15] [15:0] $end
$upscope $end
$upscope $end
$scope module regfile_tb $end
$scope module u_regfile $end
$upscope $end
$scope task init $end
$upscope $end
$scope task regRD $end
$upscope $end
$scope task regWR $end
$upscope $end
$upscope $end
$enddefinitions $end
#0
$dumpvars
bx E
bx D
bx C
bx B
bx A
bx @
bx ?
bx >
bx =
bx <
bx ;
bx :
bx 9
bx 8
bx 7
bx 6
bx 5
bx 4
bx 3
bx 2
bx 1
bx 0
b0 /
b0 .
b0 -
b0 ,
b10000 +
b10111000101111011101100110001101100100001011110111001001100101011001110110011001101001011011000110010100101110011101100110001101100100 *
bx )
0(
b0 '
b0 &
b0 %
b0 $
0#
bx "
bx !
$end
#5
bx 6
1#
#10
0#
#15
bx 6
1#
#20
0#
#25
bx 6
1#
#30
0#
#35
bx 6
1#
#40
1(
b101011101010010 )
0#
b1 5
b1 4
b1 +
#45
b0 6
b0 "
b0 0
b0 !
b0 1
1#
#50
b10 5
b10 4
b10 +
b1 &
b1 .
b1 '
b1 /
0#
#55
b1 7
1#
#60
b11 5
b11 4
b11 +
b10 &
b10 .
b10 '
b10 /
0#
#65
b10 8
1#
#70
b100 5
b100 4
b100 +
b11 &
b11 .
b11 '
b11 /
0#
#75
b11 9
1#
#80
b101 5
b101 4
b101 +
b100 &
b100 .
b100 '
b100 /
0#
#85
b100 :
1#
#90
b110 5
b110 4
b110 +
b101 &
b101 .
b101 '
b101 /
0#
#95
b101 ;
1#
#100
b111 5
b111 4
b111 +
b110 &
b110 .
b110 '
b110 /
0#
#105
b110 <
1#
#110
b1000 5
b1000 4
b1000 +
b111 &
b111 .
b111 '
b111 /
0#
#115
b111 =
1#
#120
b1001 5
b1001 4
b1001 +
b1000 &
b1000 .
b1000 '
b1000 /
0#
#125
b1000 >
1#
#130
b1010 5
b1010 4
b1010 +
b1001 &
b1001 .
b1001 '
b1001 /
0#
#135
b1001 ?
1#
#140
b1011 5
b1011 4
b1011 +
b1010 &
b1010 .
b1010 '
b1010 /
0#
#145
b1010 @
1#
#150
b1100 5
b1100 4
b1100 +
b1011 &
b1011 .
b1011 '
b1011 /
0#
#155
b1011 A
1#
#160
b1101 5
b1101 4
b1101 +
b1100 &
b1100 .
b1100 '
b1100 /
0#
#165
b1100 B
1#
#170
b1110 5
b1110 4
b1110 +
b1101 &
b1101 .
b1101 '
b1101 /
0#
#175
b1101 C
1#
#180
b1111 5
b1111 4
b1111 +
b1110 &
b1110 .
b1110 '
b1110 /
0#
#185
b1110 D
1#
#190
b0 3
b0 2
b0 +
b1111 &
b1111 .
b1111 '
b1111 /
0#
#195
b1111 E
1#
#200
b1 3
b1 2
b1 +
0(
b101001001000100 )
0#
#205
b1111 E
1#
#210
b10 3
b10 2
b10 +
b1 !
b1 1
b1 %
b1 -
b1 "
b1 0
b1 $
b1 ,
0#
#215
b1111 E
1#
#220
b11 3
b11 2
b11 +
b10 !
b10 1
b10 %
b10 -
b10 "
b10 0
b10 $
b10 ,
0#
#225
b1111 E
1#
#230
b100 3
b100 2
b100 +
b11 !
b11 1
b11 %
b11 -
b11 "
b11 0
b11 $
b11 ,
0#
#235
b1111 E
1#
#240
b101 3
b101 2
b101 +
b100 !
b100 1
b100 %
b100 -
b100 "
b100 0
b100 $
b100 ,
0#
#245
b1111 E
1#
#250
b110 3
b110 2
b110 +
b101 !
b101 1
b101 %
b101 -
b101 "
b101 0
b101 $
b101 ,
0#
#255
b1111 E
1#
#260
b111 3
b111 2
b111 +
b110 !
b110 1
b110 %
b110 -
b110 "
b110 0
b110 $
b110 ,
0#
#265
b1111 E
1#
#270
b1000 3
b1000 2
b1000 +
b111 !
b111 1
b111 %
b111 -
b111 "
b111 0
b111 $
b111 ,
0#
#275
b1111 E
1#
#280
b1001 3
b1001 2
b1001 +
b1000 !
b1000 1
b1000 %
b1000 -
b1000 "
b1000 0
b1000 $
b1000 ,
0#
#285
b1111 E
1#
#290
b1010 3
b1010 2
b1010 +
b1001 !
b1001 1
b1001 %
b1001 -
b1001 "
b1001 0
b1001 $
b1001 ,
0#
#295
b1111 E
1#
#300
b1011 3
b1011 2
b1011 +
b1010 !
b1010 1
b1010 %
b1010 -
b1010 "
b1010 0
b1010 $
b1010 ,
0#
#305
b1111 E
1#
#310
b1100 3
b1100 2
b1100 +
b1011 !
b1011 1
b1011 %
b1011 -
b1011 "
b1011 0
b1011 $
b1011 ,
0#
#315
b1111 E
1#
#320
b1101 3
b1101 2
b1101 +
b1100 !
b1100 1
b1100 %
b1100 -
b1100 "
b1100 0
b1100 $
b1100 ,
0#
#325
b1111 E
1#
#330
b1110 3
b1110 2
b1110 +
b1101 !
b1101 1
b1101 %
b1101 -
b1101 "
b1101 0
b1101 $
b1101 ,
0#
#335
b1111 E
1#
#340
b1111 3
b1111 2
b1111 +
b1110 !
b1110 1
b1110 %
b1110 -
b1110 "
b1110 0
b1110 $
b1110 ,
0#
#345
b1111 E
1#
#350
b1001001000010101 5
b0 4
b0 +
b1111 !
b1111 1
b1111 %
b1111 -
b1111 "
b1111 0
b1111 $
b1111 ,
0#
#355
b1111 E
1#
#360
1(
b0 &
b0 .
b1001001000010101 '
b1001001000010101 /
b101011101010010 )
0#
#365
b1001001000010101 6
1#
#370
b100000010001001 5
b1 4
b1 +
0(
b1001001000010101 !
b1001001000010101 1
b0 %
b0 -
b1001001000010101 "
b1001001000010101 0
b0 $
b0 ,
b101001001000100 )
0#
b0 3
b0 2
#375
b1001001000010101 6
1#
#380
1(
b1 &
b1 .
b100000010001001 '
b100000010001001 /
b101011101010010 )
0#
#385
b100000010001001 7
1#
#390
b10010000100 5
b10 4
b10 +
0(
b100000010001001 !
b100000010001001 1
b1 %
b1 -
b100000010001001 "
b100000010001001 0
b1 $
b1 ,
b101001001000100 )
0#
b1 3
b1 2
#395
b100000010001001 7
1#
#400
1(
b10 &
b10 .
b10010000100 '
b10010000100 /
b101011101010010 )
0#
#405
b10010000100 8
1#
#410
b11000111110000 5
b11 4
b11 +
0(
b10010000100 !
b10010000100 1
b10 %
b10 -
b10010000100 "
b10010000100 0
b10 $
b10 ,
b101001001000100 )
0#
b10 3
b10 2
#415
b10010000100 8
1#
#420
1(
b11 &
b11 .
b11000111110000 '
b11000111110000 /
b101011101010010 )
0#
#425
b11000111110000 9
1#
#430
b1000011010111001 5
b100 4
b100 +
0(
b11000111110000 !
b11000111110000 1
b11 %
b11 -
b11000111110000 "
b11000111110000 0
b11 $
b11 ,
b101001001000100 )
0#
b11 3
b11 2
#435
b11000111110000 9
1#
#440
1(
b100 &
b100 .
b1000011010111001 '
b1000011010111001 /
b101011101010010 )
0#
#445
b1000011010111001 :
1#
#450
b1100011011011111 5
b101 4
b101 +
0(
b1000011010111001 !
b1000011010111001 1
b100 %
b100 -
b1000011010111001 "
b1000011010111001 0
b100 $
b100 ,
b101001001000100 )
0#
b100 3
b100 2
#455
b1000011010111001 :
1#
#460
1(
b101 &
b101 .
b1100011011011111 '
b1100011011011111 /
b101011101010010 )
0#
#465
b1100011011011111 ;
1#
#470
b11001011000010 5
b110 4
b110 +
0(
b1100011011011111 !
b1100011011011111 1
b101 %
b101 -
b1100011011011111 "
b1100011011011111 0
b101 $
b101 ,
b101001001000100 )
0#
b101 3
b101 2
#475
b1100011011011111 ;
1#
#480
1(
b110 &
b110 .
b11001011000010 '
b11001011000010 /
b101011101010010 )
0#
#485
b11001011000010 <
1#
#490
b100100110111 5
b111 4
b111 +
0(
b11001011000010 !
b11001011000010 1
b110 %
b110 -
b11001011000010 "
b11001011000010 0
b110 $
b110 ,
b101001001000100 )
0#
b110 3
b110 2
#495
b11001011000010 <
1#
#500
1(
b111 &
b111 .
b100100110111 '
b100100110111 /
b101011101010010 )
0#
#505
b100100110111 =
1#
#510
b1000000011110011 5
b1000 4
b1000 +
0(
b100100110111 !
b100100110111 1
b111 %
b111 -
b100100110111 "
b100100110111 0
b111 $
b111 ,
b101001001000100 )
0#
b111 3
b111 2
#515
b100100110111 =
1#
#520
1(
b1000 &
b1000 .
b1000000011110011 '
b1000000011110011 /
b101011101010010 )
0#
#525
b1000000011110011 >
1#
#530
b1000011011010111 5
b1001 4
b1001 +
0(
b1000000011110011 !
b1000000011110011 1
b1000 %
b1000 -
b1000000011110011 "
b1000000011110011 0
b1000 $
b1000 ,
b101001001000100 )
0#
b1000 3
b1000 2
#535
b1000000011110011 >
1#
#540
1(
b1001 &
b1001 .
b1000011011010111 '
b1000011011010111 /
b101011101010010 )
0#
#545
b1000011011010111 ?
1#
#550
b1011101100100011 5
b1010 4
b1010 +
0(
b1000011011010111 !
b1000011011010111 1
b1001 %
b1001 -
b1000011011010111 "
b1000011011010111 0
b1001 $
b1001 ,
b101001001000100 )
0#
b1001 3
b1001 2
#555
b1000011011010111 ?
1#
#560
1(
b1010 &
b1010 .
b1011101100100011 '
b1011101100100011 /
b101011101010010 )
0#
#565
b1011101100100011 @
1#
#570
b1001111010001101 5
b1011 4
b1011 +
0(
b1011101100100011 !
b1011101100100011 1
b1010 %
b1010 -
b1011101100100011 "
b1011101100100011 0
b1010 $
b1010 ,
b101001001000100 )
0#
b1010 3
b1010 2
#575
b1011101100100011 @
1#
#580
1(
b1011 &
b1011 .
b1001111010001101 '
b1001111010001101 /
b101011101010010 )
0#
#585
b1001111010001101 A
1#
#590
b1111011011010100 5
b1100 4
b1100 +
0(
b1001111010001101 !
b1001111010001101 1
b1011 %
b1011 -
b1001111010001101 "
b1001111010001101 0
b1011 $
b1011 ,
b101001001000100 )
0#
b1011 3
b1011 2
#595
b1001111010001101 A
1#
#600
1(
b1100 &
b1100 .
b1111011011010100 '
b1111011011010100 /
b101011101010010 )
0#
#605
b1111011011010100 B
1#
#610
b1100011000101101 5
b1101 4
b1101 +
0(
b1111011011010100 !
b1111011011010100 1
b1100 %
b1100 -
b1111011011010100 "
b1111011011010100 0
b1100 $
b1100 ,
b101001001000100 )
0#
b1100 3
b1100 2
#615
b1111011011010100 B
1#
#620
1(
b1101 &
b1101 .
b1100011000101101 '
b1100011000101101 /
b101011101010010 )
0#
#625
b1100011000101101 C
1#
#630
b1111110011111101 5
b1110 4
b1110 +
0(
b1100011000101101 !
b1100011000101101 1
b1101 %
b1101 -
b1100011000101101 "
b1100011000101101 0
b1101 $
b1101 ,
b101001001000100 )
0#
b1101 3
b1101 2
#635
b1100011000101101 C
1#
#640
1(
b1110 &
b1110 .
b1111110011111101 '
b1111110011111101 /
b101011101010010 )
0#
#645
b1111110011111101 D
1#
#650
b110001100110111 5
b1111 4
b1111 +
0(
b1111110011111101 !
b1111110011111101 1
b1110 %
b1110 -
b1111110011111101 "
b1111110011111101 0
b1110 $
b1110 ,
b101001001000100 )
0#
b1110 3
b1110 2
#655
b1111110011111101 D
1#
#660
1(
b1111 &
b1111 .
b110001100110111 '
b110001100110111 /
b101011101010010 )
0#
#665
b110001100110111 E
1#
#670
b10000 +
0(
b110001100110111 !
b110001100110111 1
b1111 %
b1111 -
b110001100110111 "
b110001100110111 0
b1111 $
b1111 ,
b101001001000100 )
0#
b1111 3
b1111 2
