project/verilog_tutorials/project0/01_barrel_shifter/barrel_shifter.v
module barrel_shifter(
	input 	[7:0] a,
	input 	[2:0] k,
	output 	[7:0] y
);

	wire [7:0] storage0;
	wire [7:0] storage1;
	wire [7:0] storage2;

	// storage2 : 4bit shift 
	assign storage2[0] = k[2] ? a[4] : a[0];
	assign storage2[1] = k[2] ? a[5] : a[1];
	assign storage2[2] = k[2] ? a[6] : a[2];
	assign storage2[3] = k[2] ? a[7] : a[3];
	assign storage2[4] = k[2] ? a[0] : a[4];
	assign storage2[5] = k[2] ? a[1] : a[5];
	assign storage2[6] = k[2] ? a[2] : a[6];
	assign storage2[7] = k[2] ? a[3] : a[7];

	// storage1 : 2bit shift 
	assign storage1[0] = k[1] ? storage2[2] : storage2[0];
	assign storage1[1] = k[1] ? storage2[3] : storage2[1];
	assign storage1[2] = k[1] ? storage2[4] : storage2[2];
	assign storage1[3] = k[1] ? storage2[5] : storage2[3];
	assign storage1[4] = k[1] ? storage2[6] : storage2[4];
	assign storage1[5] = k[1] ? storage2[7] : storage2[5];
	assign storage1[6] = k[1] ? storage2[0] : storage2[6];
	assign storage1[7] = k[1] ? storage2[1] : storage2[7];

	// storage0 : 1bit shift 
	assign storage0[0] = k[0] ? storage1[1] : storage1[0];
	assign storage0[1] = k[0] ? storage1[2] : storage1[1];
	assign storage0[2] = k[0] ? storage1[3] : storage1[2];
	assign storage0[3] = k[0] ? storage1[4] : storage1[3];
	assign storage0[4] = k[0] ? storage1[5] : storage1[4];
	assign storage0[5] = k[0] ? storage1[6] : storage1[5];
	assign storage0[6] = k[0] ? storage1[7] : storage1[6];
	assign storage0[7] = k[0] ? storage1[0] : storage1[7];

	// final output 
	assign y = storage0;

endmodule

project/verilog_tutorials/project0/01_barrel_shifter/barrel_shifter_tb.v
`include "barrel_shifter.v"
`define  SIMCYCLE 10
`define  CLKFREQ  50

module barrel_shifter_tb;

	reg 		  clk;
	reg 	[7:0] a;
	reg 	[2:0] k;
	wire 	[7:0] y;

	barrel_shifter
	u_barrel_shifter(
		.a					(a					),
		.k					(k					),
		.y					(y					)
	);

//----------------------------------------------
// Clock 
//----------------------------------------------
	
 	always #(500/`CLKFREQ) clk = ~clk;

//----------------------------------------------
// Tasks  
//----------------------------------------------
	
	task init;
		begin 
			clk = 0;
			a 	= 0;
			k 	= 0; 
		end 
	endtask

//----------------------------------------------
// Test Stimulus   
//----------------------------------------------
	
	integer i;
	initial begin 
		init();
		
		for(i=0; i<`SIMCYCLE; i++) begin 
			
			a = 8'b0000_0100;
			k = 3'h1;

			@(posedge clk);
			#10;

			a = 8'b1111_0000;
			k = 3'h3;

			@(posedge clk);
			#10;
			
			a = 8'b0101_0101;
			k = 3'h1;

		end
	$finish;
	end 

//---------------------------------------------
// Dump VCD  
//---------------------------------------------

    reg [8*32-1:0] vcd_file;
    initial begin
        if($value$plusargs("vcd_file=%s", vcd_file)) begin
            $dumpfile(vcd_file);
            $dumpvars;
        end else begin
            $dumpfile("barrel_shifter_tb.vcd");
            $dumpvars;
        end
    end
endmodule

project/verilog_tutorials/project0/01_barrel_shifter/vcd/barrel_shifter.vcd
$date
	Tue Jul  2 17:03:30 2024
$end
$version
	Icarus Verilog
$end
$timescale
	1s
$end
$scope module barrel_shifter_tb $end
$var wire 8 ! y [7:0] $end
$var reg 8 " a [7:0] $end
$var reg 1 # clk $end
$var reg 3 $ k [2:0] $end
$var reg 256 % vcd_file [255:0] $end
$var integer 32 & i [31:0] $end
$scope module u_barrel_shifter $end
$var wire 8 ' a [7:0] $end
$var wire 3 ( k [2:0] $end
$var wire 8 ) y [7:0] $end
$var wire 8 * storage2 [7:0] $end
$var wire 8 + storage1 [7:0] $end
$var wire 8 , storage0 [7:0] $end
$upscope $end
$scope task init $end
$upscope $end
$upscope $end
$enddefinitions $end
#0
$dumpvars
b10 ,
b100 +
b100 *
b10 )
b1 (
b100 '
b0 &
b1011100010111101110110011000110110010000101111011000100110000101110010011100100110010101101100010111110111001101101000011010010110011001110100011001010111001000101110011101100110001101100100 %
b1 $
0#
b100 "
b10 !
$end
#10
1#
#20
b11110 !
b11110 )
b11110 ,
b111100 +
b11110000 *
b11 $
b11 (
b11110000 "
b11110000 '
0#
#30
1#
#40
b10 !
b10 )
b10 ,
b100 +
b100 *
b1 &
b1 $
b1 (
b100 "
b100 '
0#
#50
1#
#60
b11110 !
b11110 )
b11110 ,
b111100 +
b11110000 *
b11 $
b11 (
b11110000 "
b11110000 '
0#
#70
1#
#80
b10 !
b10 )
b10 ,
b100 +
b100 *
b10 &
b1 $
b1 (
b100 "
b100 '
0#
#90
1#
#100
b11110 !
b11110 )
b11110 ,
b111100 +
b11110000 *
b11 $
b11 (
b11110000 "
b11110000 '
0#
#110
1#
#120
b10 !
b10 )
b10 ,
b100 +
b100 *
b11 &
b1 $
b1 (
b100 "
b100 '
0#
#130
1#
#140
b11110 !
b11110 )
b11110 ,
b111100 +
b11110000 *
b11 $
b11 (
b11110000 "
b11110000 '
0#
#150
1#
#160
b10 !
b10 )
b10 ,
b100 +
b100 *
b100 &
b1 $
b1 (
b100 "
b100 '
0#
#170
1#
#180
b11110 !
b11110 )
b11110 ,
b111100 +
b11110000 *
b11 $
b11 (
b11110000 "
b11110000 '
0#
#190
1#
#200
b10 !
b10 )
b10 ,
b100 +
b100 *
b101 &
b1 $
b1 (
b100 "
b100 '
0#
#210
1#
#220
b11110 !
b11110 )
b11110 ,
b111100 +
b11110000 *
b11 $
b11 (
b11110000 "
b11110000 '
0#
#230
1#
#240
b10 !
b10 )
b10 ,
b100 +
b100 *
b110 &
b1 $
b1 (
b100 "
b100 '
0#
#250
1#
#260
b11110 !
b11110 )
b11110 ,
b111100 +
b11110000 *
b11 $
b11 (
b11110000 "
b11110000 '
0#
#270
1#
#280
b10 !
b10 )
b10 ,
b100 +
b100 *
b111 &
b1 $
b1 (
b100 "
b100 '
0#
#290
1#
#300
b11110 !
b11110 )
b11110 ,
b111100 +
b11110000 *
b11 $
b11 (
b11110000 "
b11110000 '
0#
#310
1#
#320
b10 !
b10 )
b10 ,
b100 +
b100 *
b1000 &
b1 $
b1 (
b100 "
b100 '
0#
#330
1#
#340
b11110 !
b11110 )
b11110 ,
b111100 +
b11110000 *
b11 $
b11 (
b11110000 "
b11110000 '
0#
#350
1#
#360
b10 !
b10 )
b10 ,
b100 +
b100 *
b1001 &
b1 $
b1 (
b100 "
b100 '
0#
#370
1#
#380
b11110 !
b11110 )
b11110 ,
b111100 +
b11110000 *
b11 $
b11 (
b11110000 "
b11110000 '
0#
#390
1#
#400
b10101010 !
b10101010 )
b10101010 ,
b1010101 +
b1010101 *
b1010 &
b1 $
b1 (
b1010101 "
b1010101 '
0#
