week3_sequential_logic/02_latch_vs_dff/latch.v
module latch
(
	output reg		o_q,
	input			i_d,
	input			i_clk
);

	always @(*) begin
		if(i_clk) begin
			o_q <= i_d;
		end
	end

endmodule

week3_sequential_logic/02_latch_vs_dff/dff.v
module dff
(
	output reg		o_q,
	input			i_d,
	input			i_clk
);

	always @(posedge i_clk) begin
			o_q <= i_d;
	end

endmodule

week3_sequential_logic/02_latch_vs_dff/latch_dff_tb.v
`define CLKFREQ  	100
`define SIMCYCLE 	50

`include "dff.v"
`include "latch.v"

module latch_dff_tb;

	wire		o_q_dff;
	wire		o_q_latch;
	reg			i_d;
	reg			i_clk;

	dff
	u_dff(
		.o_q				(o_q_dff			),
		.i_d				(i_d				),
		.i_clk				(i_clk				)
	);
	
	latch
	u_latch(
		.o_q				(o_q_latch			),
		.i_d				(i_d				),
		.i_clk				(i_clk				)
	);

//---------------------------------------------------
// Clock 
//---------------------------------------------------

	always #(500/`CLKFREQ) i_clk = ~i_clk;

//---------------------------------------------------
// Task  
//---------------------------------------------------

	task init;
		begin 
			i_d   = 0;
			i_clk = 0;
		end
	endtask

//---------------------------------------------------
// Test Stimulus  
//---------------------------------------------------

	integer i, j;
	initial begin 
		init();

		for(i=0; i<`SIMCYCLE; i++) begin
			j = $urandom_range(0,10);
			#((	   (j*0.1)) * 1000/`CLKFREQ);
			i_d = $urandom;
			#((1 - (j*0.1)) * 1000/`CLKFREQ);
		end
		$finish;
	end

// ---------------------------------------------------
// Dump VCD
// ---------------------------------------------------

	reg [8*32-1:0] vcd_file;
	initial begin
		if($value$plusargs("vcd_file=%s", vcd_file)) begin
			$dumpfile(vcd_file);
			$dumpvars;
		end else begin 
			$dumpfile("latch_dff_tb.vcd");
			$dumpvars;
		end
	end
endmodule

week3_sequential_logic/02_latch_vs_dff/vcd/latch_dff.vcd
$date
	Tue Jun 25 09:22:36 2024
$end
$version
	Icarus Verilog
$end
$timescale
	1s
$end
$scope module latch_dff_tb $end
$var wire 1 ! o_q_latch $end
$var wire 1 " o_q_dff $end
$var reg 1 # i_clk $end
$var reg 1 $ i_d $end
$var reg 256 % vcd_file [255:0] $end
$var integer 32 & i [31:0] $end
$var integer 32 ' j [31:0] $end
$scope module u_dff $end
$var wire 1 # i_clk $end
$var wire 1 $ i_d $end
$var reg 1 " o_q $end
$upscope $end
$scope module u_latch $end
$var wire 1 # i_clk $end
$var wire 1 $ i_d $end
$var reg 1 ! o_q $end
$upscope $end
$scope task init $end
$upscope $end
$upscope $end
$enddefinitions $end
#0
$dumpvars
b110 '
b0 &
b101110001011110111011001100011011001000010111101101100011000010111010001100011011010000101111101100100011001100110011000101110011101100110001101100100 %
0$
0#
x"
x!
$end
#5
0"
0!
1#
#6
1!
1$
#10
b0 '
b1 &
0#
#15
1"
1#
#20
0#
b101 '
b10 &
#25
1#
#30
0#
b10 '
b11 &
#32
0$
#35
0"
0!
1#
#40
0#
b101 '
b100 &
#45
1"
1!
1#
1$
#50
0#
b1000 '
b101 &
#55
1#
#60
b1010 '
b110 &
0#
#65
1#
#70
b111 &
0#
0$
#75
0"
0!
1#
#80
b100 '
b1000 &
0#
#85
1#
#90
0#
b1010 '
b1001 &
#95
1#
#100
b0 '
b1010 &
0#
1$
#105
1"
1!
1#
#110
0#
b1010 '
b1011 &
#115
1#
#120
b100 '
b1100 &
0#
0$
#124
1$
#125
1#
#130
0#
b111 '
b1101 &
#135
1#
#140
b0 '
b1110 &
0#
#145
1#
#150
0#
b10 '
b1111 &
#152
0$
#155
0"
0!
1#
#160
0#
b10000 &
#165
1#
#170
0#
b1001 '
b10001 &
#175
1#
#179
1!
1$
#180
b11 '
b10010 &
0#
#185
1"
1#
#190
0#
b0 '
b10011 &
#195
1#
#200
0#
b111 '
b10100 &
#205
1#
#210
0$
b0 '
b10101 &
0#
#215
0"
0!
1#
#220
0#
b110 '
b10110 &
#225
1#
#226
1!
1$
#230
b10111 &
0#
#235
1"
1#
#236
0!
0$
#240
b100 '
b11000 &
0#
#245
0"
1#
#250
0#
b1010 '
b11001 &
#255
1#
#260
b110 '
b11010 &
0#
#265
1#
#270
b1000 '
b11011 &
0#
#275
1#
#278
1!
1$
#280
b1010 '
b11100 &
0#
#285
1"
1#
#290
b1001 '
b11101 &
0#
0$
#295
0"
0!
1#
#300
b100 '
b11110 &
0#
#305
1#
#310
1$
0#
b0 '
b11111 &
#315
1"
1!
1#
#320
0#
b1000 '
b100000 &
#325
1#
#330
b1 '
b100001 &
0#
#331
0$
#335
0"
0!
1#
#340
0#
b10 '
b100010 &
#342
1$
#345
1"
1!
1#
#350
0#
b1010 '
b100011 &
#355
1#
#360
b111 '
b100100 &
0#
#365
1#
#367
0!
0$
#370
b1000 '
b100101 &
0#
#375
0"
1#
#378
1!
1$
#380
b1010 '
b100110 &
0#
#385
1"
1#
#390
b11 '
b100111 &
0#
#393
0$
#395
0"
0!
1#
#400
0#
b1 '
b101000 &
#401
1$
#405
1"
1!
1#
#410
0#
b101001 &
#411
0$
#415
0"
0!
1#
#420
0#
b100 '
b101010 &
#424
1$
#425
1"
1!
1#
#430
0#
b1000 '
b101011 &
#435
1#
#438
0!
0$
#440
b100 '
b101100 &
0#
#445
0"
1#
#450
0#
b10 '
b101101 &
#452
1$
#455
1"
1!
1#
#460
0#
b101 '
b101110 &
#465
0"
0!
1#
0$
#470
0#
b111 '
b101111 &
#475
1#
#477
1!
1$
#480
b110 '
b110000 &
0#
#485
1"
1#
#490
b1000 '
b110001 &
0#
#495
1#
#498
0!
0$
#500
b110010 &
0#
